{
    "type": "FeatureCollection",
    "licence": "Data \u00a9 OpenStreetMap contributors, ODbL 1.0. https://osm.org/copyright",
    "features": [
        {
            "type": "Feature",
            "properties": {
                "place_id": 297573910,
                "osm_type": "relation",
                "osm_id": 2012495,
                "display_name": "Abondant, Dreux, Eure-et-Loir, Centre-Val de Loire, France m\u00e9tropolitaine, 28410, France",
                "place_rank": 16,
                "category": "boundary",
                "type": "administrative",
                "importance": 0.6264793805329572,
                "icon": "https://nominatim.openstreetmap.org/ui/mapicons/poi_boundary_administrative.p.20.png"
            },
            "bbox": [
                1.3663469,
                48.7650244,
                1.4813886,
                48.8314601
            ],
            "geometry": {
                "type": "Point",
                "coordinates": [
                    1.4411738,
                    48.7822754
                ]
            }
        }
    ]
}