{
    "type": "FeatureCollection",
    "licence": "Data \u00a9 OpenStreetMap contributors, ODbL 1.0. https://osm.org/copyright",
    "features": [
        {
            "type": "Feature",
            "properties": {
                "place_id": 297876916,
                "osm_type": "relation",
                "osm_id": 135589,
                "display_name": "Deauville, Lisieux, Calvados, Normandie, France m\u00e9tropolitaine, 14800, France",
                "place_rank": 16,
                "category": "boundary",
                "type": "administrative",
                "importance": 0.6831642994993394,
                "icon": "https://nominatim.openstreetmap.org/ui/mapicons/poi_boundary_administrative.p.20.png"
            },
            "bbox": [
                0.0581477,
                49.3391576,
                0.091915,
                49.3687248
            ],
            "geometry": {
                "type": "Point",
                "coordinates": [
                    0.0752778,
                    49.36
                ]
            }
        }
    ]
}